
<item>
<title>[COLOR gray][COLOR red]• [/COLOR] [B]Temporada 1[/B][/COLOR]</title>
<link>$doregex[makelist]</link>
<regex>
  <name>makelist</name>
  <listrepeat><![CDATA[
        <title>[COLOR red]  [makelist.param3][/COLOR]</title>
        <link>$doregex[getUrl]</link>
    <thumbnail>https://orig06.deviantart.net/a3b6/f/2014/282/a/a/black_ish_season_1_v_1_by_nc_esseh-d825rlz.png</thumbnail>
        <fanart>https://images3.alphacoders.com/598/598492.jpg</fanart>
        ]]></listrepeat>
<expres><![CDATA[href="\/.*,(.*?),list.*\n.*\n.*\n.*href="\/([^"]*)".*?>(.*?)<]]></expres>
<page>http://diskokosmiko.mx/SeriesHD/blackish-t1-39042/list,1,2</page>
<cookieJar></cookieJar>
</regex>
<regex>
<name>getUrl</name>
<expres>DownloadUrl":"([^"]+)<expres>
<page>http://diskokosmiko.mx/action/DownloadFile?location=fi&amp;f=[makelist.param1]</page>
<rawpost>fileId=[makelist.param1]&amp;__RequestVerificationToken=$doregex[tok]</rawpost>
<referer>http://diskokosmiko.mx/[makelist.param2]</referer>
<connection>keep-alive</connection>
<accept>*/*</accept>
<X-Req>XMLHttpRequest</X-Req>
<cookieJar></cookieJar>
</regex>
<regex>
<name>tok</name>
<expres>DownloadFile.*RequestVerificationToken.*?value="([^"]+)<expres>
<page>http://diskokosmiko.mx/[makelist.param2]</page>
<referer>http://diskokosmiko.mx/SeriesHD/blackish-t1-39042/list,1,2<referer>
<connection>keep-alive</connection>
<cookieJar></cookieJar>
</regex>
<thumbnail>https://orig06.deviantart.net/a3b6/f/2014/282/a/a/black_ish_season_1_v_1_by_nc_esseh-d825rlz.png</thumbnail>
<fanart>https://images3.alphacoders.com/598/598492.jpg</fanart>
</item>

<item>
<title>[COLOR gray][COLOR red]• [/COLOR] [B]Temporada 2[/B][/COLOR]</title>
<link>$doregex[makelist]</link>
<regex>
  <name>makelist</name>
  <listrepeat><![CDATA[
        <title>[COLOR red]  [makelist.param3][/COLOR]</title>
        <link>$doregex[getUrl]</link>
    <thumbnail>https://orig06.deviantart.net/a3b6/f/2014/282/a/a/black_ish_season_1_v_1_by_nc_esseh-d825rlz.png</thumbnail>
        <fanart>https://images3.alphacoders.com/598/598492.jpg</fanart>
        ]]></listrepeat>
<expres><![CDATA[href="\/.*,(.*?),list.*\n.*\n.*\n.*href="\/([^"]*)".*?>(.*?)<]]></expres>
<page>http://diskokosmiko.mx/SeriesHD/blackish-t2-39043/list,1,2</page>
<cookieJar></cookieJar>
</regex>
<regex>
<name>getUrl</name>
<expres>DownloadUrl":"([^"]+)<expres>
<page>http://diskokosmiko.mx/action/DownloadFile?location=fi&amp;f=[makelist.param1]</page>
<rawpost>fileId=[makelist.param1]&amp;__RequestVerificationToken=$doregex[tok]</rawpost>
<referer>http://diskokosmiko.mx/[makelist.param2]</referer>
<connection>keep-alive</connection>
<accept>*/*</accept>
<X-Req>XMLHttpRequest</X-Req>
<cookieJar></cookieJar>
</regex>
<regex>
<name>tok</name>
<expres>DownloadFile.*RequestVerificationToken.*?value="([^"]+)<expres>
<page>http://diskokosmiko.mx/[makelist.param2]</page>
<referer>http://diskokosmiko.mx/SeriesHD/blackish-t2-39043/list,1,2<referer>
<connection>keep-alive</connection>
<cookieJar></cookieJar>
</regex>
<thumbnail>https://orig06.deviantart.net/a3b6/f/2014/282/a/a/black_ish_season_1_v_1_by_nc_esseh-d825rlz.png</thumbnail>
<fanart>https://images3.alphacoders.com/598/598492.jpg</fanart>
</item>

<item>
<title>[COLOR gray][COLOR red]• [/COLOR] [B]Temporada 3[/B][/COLOR]</title>
<link>$doregex[makelist]</link>
<regex>
  <name>makelist</name>
  <listrepeat><![CDATA[
        <title>[COLOR red]  [makelist.param3][/COLOR]</title>
        <link>$doregex[getUrl]</link>
    <thumbnail>https://orig06.deviantart.net/a3b6/f/2014/282/a/a/black_ish_season_1_v_1_by_nc_esseh-d825rlz.png</thumbnail>
        <fanart>https://images3.alphacoders.com/598/598492.jpg</fanart>
        ]]></listrepeat>
<expres><![CDATA[href="\/.*,(.*?),list.*\n.*\n.*\n.*href="\/([^"]*)".*?>(.*?)<]]></expres>
<page>http://diskokosmiko.mx/SeriesHD/black-ish-t3-d-43674</page>
<cookieJar></cookieJar>
</regex>
<regex>
<name>getUrl</name>
<expres>DownloadUrl":"([^"]+)<expres>
<page>http://diskokosmiko.mx/action/DownloadFile?location=fi&amp;f=[makelist.param1]</page>
<rawpost>fileId=[makelist.param1]&amp;__RequestVerificationToken=$doregex[tok]</rawpost>
<referer>http://diskokosmiko.mx/[makelist.param2]</referer>
<connection>keep-alive</connection>
<accept>*/*</accept>
<X-Req>XMLHttpRequest</X-Req>
<cookieJar></cookieJar>
</regex>
<regex>
<name>tok</name>
<expres>DownloadFile.*RequestVerificationToken.*?value="([^"]+)<expres>
<page>http://diskokosmiko.mx/[makelist.param2]</page>
<referer>http://diskokosmiko.mx/SeriesHD/black-ish-t3-d-43674<referer>
<connection>keep-alive</connection>
<cookieJar></cookieJar>
</regex>
<thumbnail>https://orig06.deviantart.net/a3b6/f/2014/282/a/a/black_ish_season_1_v_1_by_nc_esseh-d825rlz.png</thumbnail>
<fanart>https://images3.alphacoders.com/598/598492.jpg</fanart>
</item>
